EmoLexGram/EmoLexGram.py
EmoLexGram/__init__.py
EmoLexGram-0.0.1.dist-info/LICENSE
EmoLexGram-0.0.1.dist-info/METADATA
EmoLexGram-0.0.1.dist-info/WHEEL
EmoLexGram-0.0.1.dist-info/top_level.txt
EmoLexGram-0.0.1.dist-info/RECORD
