Metadata-Version: 2.1
Name: EmoLexGram
Version: 0.0.1
Summary: EmoLexGram is a python package for text-based emotion classification
Home-page: https://github.com/mary123mary/EmoLexGram
Author: Moksha Thisarani
Author-email: moksha.util@gmail.com
License: MIT
Platform: UNKNOWN
Classifier: License :: OSI Approved :: MIT License
Classifier: Programming Language :: Python
Classifier: Programming Language :: Python :: 3.5
Classifier: Programming Language :: Python :: 3.6
Classifier: Programming Language :: Python :: 3.7
Classifier: Topic :: Software Development :: Libraries
Classifier: Topic :: Software Development :: Libraries :: Python Modules
Classifier: Intended Audience :: Developers
Requires-Python: >=3.5
License-File: LICENSE
Requires-Dist: pandas
Requires-Dist: nltk
Requires-Dist: requests
